{ "backgroundcolor":"#808080",
 "height":15,
 "layers":[
        {
         "data":[0, 0, 0, 0, 0, 0, 0, 0, 0, 0, 0, 0, 0, 0, 0, 0, 0, 0, 0, 0, 0, 0, 0, 0, 0, 0, 0, 0, 0, 0, 0, 0, 0, 0, 0, 0, 0, 0, 0, 0, 0, 0, 0, 0, 0, 0, 0, 0, 0, 0, 0, 0, 0, 0, 0, 5, 6, 6, 6, 6, 6, 6, 6, 8, 0, 0, 0, 0, 0, 0, 0, 0, 0, 0, 0, 0, 0, 0, 0, 0, 15, 11, 11, 11, 11, 11, 12, 17, 18, 5, 6, 6, 6, 6, 6, 6, 8, 0, 0, 0, 0, 0, 0, 0, 0, 15, 11, 16, 16, 16, 11, 12, 12, 18, 10, 11, 11, 12, 11, 16, 11, 18, 0, 0, 0, 0, 0, 0, 0, 0, 15, 11, 16, 17, 11, 12, 17, 12, 11, 11, 11, 11, 11, 12, 12, 11, 18, 0, 0, 0, 0, 0, 0, 0, 0, 15, 11, 12, 11, 12, 12, 17, 12, 11, 11, 11, 16, 11, 12, 17, 16, 18, 0, 0, 0, 0, 0, 0, 0, 0, 15, 11, 11, 12, 11, 11, 11, 11, 11, 11, 11, 11, 11, 11, 11, 12, 18, 0, 0, 0, 0, 0, 0, 0, 0, 15, 11, 11, 11, 16, 16, 11, 16, 16, 16, 16, 16, 16, 16, 16, 17, 18, 0, 0, 0, 0, 0, 0, 0, 0, 15, 11, 16, 16, 16, 17, 16, 16, 17, 11, 16, 16, 16, 16, 16, 16, 18, 0, 0, 0, 0, 0, 0, 0, 0, 15, 11, 11, 11, 11, 16, 16, 17, 18, 10, 16, 17, 12, 12, 12, 12, 18, 0, 0, 0, 0, 0, 0, 0, 0, 15, 16, 16, 16, 16, 16, 17, 12, 18, 10, 16, 17, 17, 17, 17, 17, 18, 0, 0, 0, 0, 0, 0, 0, 0, 20, 21, 21, 21, 21, 21, 21, 21, 23, 10, 11, 12, 17, 17, 17, 17, 18, 0, 0, 0, 0, 0, 0, 0, 0, 0, 0, 0, 0, 0, 0, 0, 0, 0, 20, 21, 21, 21, 21, 22, 21, 23, 0, 0, 0, 0, 0, 0, 0, 0, 0, 0, 0, 0, 0, 0, 0, 0, 0, 0, 0, 0, 0, 0, 0, 0, 0, 0, 0, 0],
         "height":15,
         "name":"backgroundLayer",
         "opacity":1,
         "type":"tilelayer",
         "visible":true,
         "width":25,
         "x":0,
         "y":0
        }, 
        {
         "draworder":"topdown",
         "height":0,
         "name":"objectsLayer",
         "objects":[
                {
                 "gid":3,
                 "height":16,
                 "id":3,
                 "name":"playerStart",
                 "properties":
                    {
                     "spriteName":"player_start",
                     "type":"playerStart"
                    },
                 "rotation":0,
                 "type":"playerStart",
                 "visible":true,
                 "width":16,
                 "x":393.933333333333,
                 "y":459.168
                }, 
                {
                 "gid":4,
                 "height":16,
                 "id":4,
                 "name":"bottle",
                 "properties":
                    {
                     "spriteName":"pickup_bottle",
                     "type":"pickup"
                    },
                 "rotation":0,
                 "type":"pickup",
                 "visible":true,
                 "width":16,
                 "x":387,
                 "y":272
                }],
         "opacity":1,
         "type":"objectgroup",
         "visible":true,
         "width":0,
         "x":0,
         "y":0
        }, 
        {
         "color":"#00ff00",
         "draworder":"topdown",
         "height":0,
         "name":"collisionsLayer",
         "objects":[
                {
                 "height":10.6060606060605,
                 "id":9,
                 "name":"wall",
                 "properties":
                    {
                     "spriteName":"collision",
                     "type":"collision"
                    },
                 "rotation":0,
                 "type":"collision",
                 "visible":true,
                 "width":512,
                 "x":896.363636363636,
                 "y":886.727272727273
                }, 
                {
                 "height":251.939393939394,
                 "id":18,
                 "name":"wall",
                 "properties":
                    {
                     "spriteName":"collision",
                     "type":"collision"
                    },
                 "rotation":0,
                 "type":"collision",
                 "visible":true,
                 "width":18.3030303030305,
                 "x":887.030303030303,
                 "y":637.393939393939
                }, 
                {
                 "height":189.333333333333,
                 "id":21,
                 "name":"wall",
                 "properties":
                    {
                     "spriteName":"collision",
                     "type":"collision"
                    },
                 "rotation":0,
                 "type":"collision",
                 "visible":true,
                 "width":18.3030303030305,
                 "x":888.363636363636,
                 "y":130.666666666667
                }, 
                {
                 "height":693.333333333333,
                 "id":22,
                 "name":"wall",
                 "properties":
                    {
                     "spriteName":"collision",
                     "type":"collision"
                    },
                 "rotation":0,
                 "type":"collision",
                 "visible":true,
                 "width":18.3030303030305,
                 "x":1397.69696969697,
                 "y":194.666666666667
                }, 
                {
                 "height":700,
                 "id":23,
                 "name":"wall",
                 "properties":
                    {
                     "spriteName":"collision",
                     "type":"collision"
                    },
                 "rotation":0,
                 "type":"collision",
                 "visible":true,
                 "width":18.3030303030305,
                 "x":311.030303030303,
                 "y":129.333333333333
                }, 
                {
                 "height":9.39393939393935,
                 "id":24,
                 "name":"wall",
                 "properties":
                    {
                     "spriteName":"collision",
                     "type":"collision"
                    },
                 "rotation":0,
                 "type":"collision",
                 "visible":true,
                 "width":499.030303030303,
                 "x":905.333333333333,
                 "y":190.666666666667
                }, 
                {
                 "height":9.39393939393935,
                 "id":25,
                 "name":"wall",
                 "properties":
                    {
                     "spriteName":"collision",
                     "type":"collision"
                    },
                 "rotation":0,
                 "type":"collision",
                 "visible":true,
                 "width":564,
                 "x":329.333333333333,
                 "y":125.333333333333
                }, 
                {
                 "height":9.39393939393935,
                 "id":26,
                 "name":"wall",
                 "properties":
                    {
                     "spriteName":"collision",
                     "type":"collision"
                    },
                 "rotation":0,
                 "type":"collision",
                 "visible":true,
                 "width":564,
                 "x":322.666666666667,
                 "y":821.333333333333
                }],
         "opacity":1,
         "type":"objectgroup",
         "visible":true,
         "width":0,
         "x":0,
         "y":0
        }],
 "nextobjectid":27,
 "orientation":"orthogonal",
 "properties":
    {

    },
 "renderorder":"right-down",
 "tileheight":64,
 "tilesets":[
        {
         "firstgid":1,
         "image":"..\/building\/inside\/tiles.png",
         "imageheight":16,
         "imagewidth":64,
         "margin":0,
         "name":"tiles",
         "properties":
            {

            },
         "spacing":0,
         "tileheight":16,
         "tileproperties":
            {
             "0":
                {
                 "type":"floor"
                },
             "1":
                {
                 "type":"wall"
                },
             "2":
                {
                 "type":"playerStart"
                }
            },
         "tilewidth":16
        }, 
        {
         "firstgid":5,
         "image":"..\/building\/inside\/tile_inside_black_tiles.png",
         "imageheight":256,
         "imagewidth":320,
         "margin":0,
         "name":"building_inside_black",
         "properties":
            {

            },
         "spacing":0,
         "tileheight":64,
         "tileproperties":
            {
             "14":
                {
                 "type":"interaction"
                },
             "4":
                {
                 "spriteName":"collision",
                 "type":"collision"
                },
             "9":
                {
                 "type":"travel"
                }
            },
         "tilewidth":64
        }],
 "tilewidth":64,
 "version":1,
 "width":25
}